{
  "version": "5.2.1",
  "flags": {},
  "shapes": [
    {
      "label": "edible amaranth",
      "points": [
        [
          248.2051282051282,
          216.9230769230769
        ],
        [
          276.41025641025647,
          253.33333333333331
        ]
      ],
      "group_id": null,
      "description": "",
      "shape_type": "rectangle",
      "flags": {}
    },
    {
      "label": "1",
      "points": [
        [
          266.66666666666663,
          237.43589743589743
        ]
      ],
      "group_id": null,
      "description": "",
      "shape_type": "point",
      "flags": {}
    },
    {
      "label": "other weeds",
      "points": [
        [
          326.1538461538462,
          67.6923076923077
        ],
        [
          346.66666666666663,
          90.25641025641026
        ]
      ],
      "group_id": null,
      "description": "",
      "shape_type": "rectangle",
      "flags": {}
    },
    {
      "label": "1",
      "points": [
        [
          337.948717948718,
          80.0
        ]
      ],
      "group_id": null,
      "description": "",
      "shape_type": "point",
      "flags": {}
    }
  ],
  "imagePath": "..\\img\\83_light.png",
  "imageData": null,
  "imageHeight": 480,
  "imageWidth": 640
}